opentelemetry/instrumentation/llamaindex/__init__.py
opentelemetry/instrumentation/llamaindex/base_agent_instrumentor.py
opentelemetry/instrumentation/llamaindex/base_embedding_instrumentor.py
opentelemetry/instrumentation/llamaindex/base_retriever_instrumentor.py
opentelemetry/instrumentation/llamaindex/base_synthesizer_instrumentor.py
opentelemetry/instrumentation/llamaindex/base_tool_instrumentor.py
opentelemetry/instrumentation/llamaindex/config.py
opentelemetry/instrumentation/llamaindex/custom_llm_instrumentor.py
opentelemetry/instrumentation/llamaindex/dispatcher_wrapper.py
opentelemetry/instrumentation/llamaindex/event_emitter.py
opentelemetry/instrumentation/llamaindex/event_models.py
opentelemetry/instrumentation/llamaindex/llamaparse_instrumentor.py
opentelemetry/instrumentation/llamaindex/query_pipeline_instrumentor.py
opentelemetry/instrumentation/llamaindex/retriever_query_engine_instrumentor.py
opentelemetry/instrumentation/llamaindex/span_utils.py
opentelemetry/instrumentation/llamaindex/utils.py
opentelemetry/instrumentation/llamaindex/version.py
opentelemetry_instrumentation_llamaindex-0.51.1.dist-info/METADATA
opentelemetry_instrumentation_llamaindex-0.51.1.dist-info/WHEEL
opentelemetry_instrumentation_llamaindex-0.51.1.dist-info/entry_points.txt
opentelemetry_instrumentation_llamaindex-0.51.1.dist-info/RECORD
